pycounts_fh/__init__.py
pycounts_fh/plotting.py
pycounts_fh/pycounts_fh.py
pycounts_fh-0.1.2.dist-info/LICENSE
pycounts_fh-0.1.2.dist-info/METADATA
pycounts_fh-0.1.2.dist-info/WHEEL
pycounts_fh-0.1.2.dist-info/RECORD
