Metadata-Version: 2.1
Name: pycounts_fh
Version: 0.1.2
Summary: Calculate Word counts in a text file.
License: MIT
Author: Farrandi Hernando
Requires-Python: >=3.9
Classifier: License :: OSI Approved :: MIT License
Classifier: Programming Language :: Python :: 3
Classifier: Programming Language :: Python :: 3.9
Classifier: Programming Language :: Python :: 3.10
Classifier: Programming Language :: Python :: 3.11
Classifier: Programming Language :: Python :: 3.12
Requires-Dist: matplotlib (>=3.8.2)
